{
  "hash": "0e7a41c0",
  "configHash": "e3001f9a",
  "lockfileHash": "3391e4c1",
  "browserHash": "c12dbae6",
  "optimized": {
    "react/jsx-dev-runtime": {
      "src": "../../node_modules/react/jsx-dev-runtime.js",
      "file": "react_jsx-dev-runtime.js",
      "fileHash": "e6e8f1e7",
      "needsInterop": true
    },
    "react": {
      "src": "../../node_modules/react/index.js",
      "file": "react.js",
      "fileHash": "ba0e003b",
      "needsInterop": true
    },
    "react-dom/client": {
      "src": "../../node_modules/react-dom/client.js",
      "file": "react-dom_client.js",
      "fileHash": "c2743faa",
      "needsInterop": true
    }
  },
  "chunks": {
    "chunk-B2WE2YPZ": {
      "file": "chunk-B2WE2YPZ.js"
    }
  }
}